notify_to_cisco_webex/__init__.py
notify_to_cisco_webex/__main__.py
notify_to_cisco_webex/notify_to_cisco_webex.py
notify_to_cisco_webex-0.0.7.dist-info/licenses/LICENSE
notify_to_cisco_webex-0.0.7.dist-info/METADATA
notify_to_cisco_webex-0.0.7.dist-info/WHEEL
notify_to_cisco_webex-0.0.7.dist-info/entry_points.txt
notify_to_cisco_webex-0.0.7.dist-info/top_level.txt
notify_to_cisco_webex-0.0.7.dist-info/RECORD
