Metadata-Version: 2.4
Name: notify-to-cisco-webex
Version: 0.0.7
Summary: Send messages and files to Cisco Webex.
Author-email: sig9org <sig9@sig9.org>
License: MIT License
Project-URL: Homepage, https://github.com/sig9org/notify-to-cisco-webex
Project-URL: Repository, https://github.com/sig9org/notify-to-cisco-webex
Project-URL: Issues, https://github.com/sig9org/notify-to-cisco-webex/issues
Keywords: cisco,webex,tool,chat,notification,notify,message
Classifier: Development Status :: 3 - Alpha
Classifier: Intended Audience :: Developers
Classifier: Intended Audience :: System Administrators
Classifier: License :: OSI Approved :: MIT License
Classifier: Operating System :: OS Independent
Classifier: Programming Language :: Python :: 3
Classifier: Programming Language :: Python :: 3.10
Classifier: Programming Language :: Python :: 3.11
Classifier: Programming Language :: Python :: 3.12
Classifier: Programming Language :: Python :: 3.13
Classifier: Programming Language :: Python :: 3.14
Classifier: Topic :: System :: Systems Administration
Classifier: Topic :: Utilities
Requires-Python: >=3.10
License-File: LICENSE
Requires-Dist: httpx>=0.28.1
Requires-Dist: python-dotenv>=1.2.1
Dynamic: license-file
